sql_athame/__init__.py
sql_athame/base.py
sql_athame/dataclasses.py
sql_athame/escape.py
sql_athame/py.typed
sql_athame/sqlalchemy.py
sql_athame/types.py
sql_athame-0.3.16.dist-info/LICENSE
sql_athame-0.3.16.dist-info/WHEEL
sql_athame-0.3.16.dist-info/METADATA
sql_athame-0.3.16.dist-info/RECORD
