Metadata-Version: 2.1
Name: sql-athame
Version: 0.3.16
Summary: Python tool for slicing and dicing SQL
Home-page: https://github.com/bdowning/sql-athame
License: MIT
Author: Brian Downing
Author-email: bdowning@lavos.net
Requires-Python: >=3.7,<4.0
Classifier: License :: OSI Approved :: MIT License
Classifier: Programming Language :: Python :: 3
Classifier: Programming Language :: Python :: 3.7
Classifier: Programming Language :: Python :: 3.8
Classifier: Programming Language :: Python :: 3.9
Provides-Extra: asyncpg
Requires-Dist: asyncpg; extra == "asyncpg"
Requires-Dist: typing-extensions
Project-URL: Repository, https://github.com/bdowning/sql-athame
